qfilters/decorators.py
qfilters/utils.py
qfilters/__init__.py
qfilters/exotic_types.py
qfilters/base_types.py
qfilters/containers.py
qfilters-0.1.dist-info/METADATA
qfilters-0.1.dist-info/WHEEL
qfilters-0.1.dist-info/RECORD
qfilters-0.1.dist-info/DESCRIPTION.rst
qfilters-0.1.dist-info/metadata.json
qfilters-0.1.dist-info/top_level.txt
