Metadata-Version: 2.0
Name: qfilters
Version: 0.1
Summary: Filters for django
Home-page: https://github.com/abetkin/django-qfilter
Author: abetkin
Author-email: abvit89@gmail.com
License: MIT
Keywords: django filters
Platform: UNKNOWN
Classifier: Development Status :: 3 - Alpha
Classifier: Intended Audience :: Developers
Classifier: License :: MIT License
Classifier: Programming Language :: Python :: 2.7
Classifier: Programming Language :: Python :: 3.3
Classifier: Programming Language :: Python :: 3.4
Requires-Dist: django
